Metadata-Version: 1.0
Name: dist-binoGauss
Version: 0.1
Summary: Gaussian distributions
Home-page: UNKNOWN
Author: Sharon Olatunji
Author-email: dolivon555@gmail.com
License: UNKNOWN
Platform: UNKNOWN
